OWCK/OWCK.py
OWCK/OWCK_slave.py
OWCK/__init__.py
OWCK/gpr.old2.py
OWCK/gpr.py
OWCK/gprhao.py
OWCK/grphao.py
OWCK/utils.py
OWCK/flame/__init__.py
OWCK/flame/flame.py
OWCK/flame/testflame.py
OWCK-1.5.8.dist-info/DESCRIPTION.rst
OWCK-1.5.8.dist-info/METADATA
OWCK-1.5.8.dist-info/RECORD
OWCK-1.5.8.dist-info/WHEEL
OWCK-1.5.8.dist-info/metadata.json
OWCK-1.5.8.dist-info/top_level.txt
