Metadata-Version: 2.0
Name: OWCK
Version: 1.5.8
Summary: Optimal Weighted Kriging / Gaussian Process
Home-page: https://github.com/Basvanstein/OWCK
Author: Bas van Stein and Hao Wang
Author-email: b.van.stein@liacs.leidenuniv.nl
License: GNUv2
Keywords: kriging guassian-process data-mining big-data
Platform: UNKNOWN
Classifier: Development Status :: 4 - Beta
Classifier: Intended Audience :: Science/Research
Classifier: Topic :: Scientific/Engineering
Classifier: License :: OSI Approved :: GNU General Public License v2 (GPLv2)
Classifier: Programming Language :: Python :: 2
Classifier: Programming Language :: Python :: 2.6
Classifier: Programming Language :: Python :: 2.7
Requires-Dist: numpy
Requires-Dist: pandas
Requires-Dist: scikit-fuzzy
Requires-Dist: scikit-learn
Provides-Extra: dev
Requires-Dist: check-manifest; extra == 'dev'
Provides-Extra: test
Requires-Dist: coverage; extra == 'test'
